libmv/__init__.py
libmv/__main__.py
libmv/command.py
libmv/config.py
libmv/dagops_daemon.py
libmv/record.py
libmv/server.py
libmv/util.py
libmv/watch.py
libmv/image/__init__.py
libmv/image/__main__.py
libmv/pitch/__init__.py
libmv/pitch/__main__.py
libmv/pitch/algorithms.py
libmv/pitch/evaluation.py
libmv/video/__init__.py
libmv/video/__main__.py
libmv/video/ffmpeg_util.py
libmv-0.4.2.dist-info/METADATA
libmv-0.4.2.dist-info/WHEEL
libmv-0.4.2.dist-info/entry_points.txt
libmv-0.4.2.dist-info/top_level.txt
libmv-0.4.2.dist-info/RECORD
